MANIFEST.in
README.rst
pytest.ini
requirements.txt
setup.py
reliure/__init__.py
reliure/engine.py
reliure/exceptions.py
reliure/offline.py
reliure/options.py
reliure/pipeline.py
reliure/schema.py
reliure/types.py
reliure/validators.py
reliure/web.py
reliure.egg-info/PKG-INFO
reliure.egg-info/SOURCES.txt
reliure.egg-info/dependency_links.txt
reliure.egg-info/pbr.json
reliure.egg-info/requires.txt
reliure.egg-info/top_level.txt
reliure/utils/__init__.py
reliure/utils/cli.py
reliure/utils/i18n.py
reliure/utils/log.py
reliure/utils/validators.py