Metadata-Version: 1.1
Name: reliure
Version: 16.12.r0
Summary: Minimal framework to manage data processing pipelines
Home-page: https://github.com/kodexlab/reliure
Author: KodexLab
Author-email: contact@kodexlab.com
License: UNKNOWN
Platform: UNKNOWN
Classifier: Programming Language :: Python
Classifier: Development Status :: 4 - Beta
Classifier: License :: OSI Approved :: GNU Library or Lesser General Public License (LGPL)
Classifier: Operating System :: OS Independent
Classifier: Programming Language :: Python :: 3
Classifier: Programming Language :: Python :: 2.7
Classifier: Topic :: Scientific/Engineering
Classifier: Topic :: Software Development :: Libraries :: Application Frameworks
